Workbook

Sheet Dashboard
A1: PSEG Long Island - Billing Analysis
A2: Source: Usage__7_.csv | Data 2025-05-30 to 2026-05-29 | 8 cycle(s) | Generated 2026-05-31
A4: BILLING CYCLE | B4: Cycle 1 | C4: Cycle 2 | D4: Cycle 3 | E4: Cycle 4 | F4: Cycle 5 | G4: Cycle 6 | H4: Cycle 7 | I4: Cycle 8 | J4: TOTAL
A5: Service period | B5: 05/30/25-11/14/25 | C5: 11/15/25-12/15/25 | D5: 12/16/25-01/16/26 | E5: 01/17/26-02/13/26 | F5: 02/14/26-03/16/26 | G5: 03/17/26-04/16/26 | H5: 04/17/26-05/15/26 | I5: 05/16/26-05/29/26 | J5: All cycles
A6: USAGE
A7: Days | B7: 169 | C7: 31 | D7: 32 | E7: 28 | F7: 31 | G7: 31 | H7: 29 | I7: 14 | J7: =SUM(B7:I7) -> 365
A8: Net consumption (kWh) | B8: 5265.02 | C8: 2863.91 | D8: 3667.56 | E8: 3006.94 | F8: 3219.54 | G8: 1781.77 | H8: 1119.09 | I8: 179.15 | J8: =SUM(B8:I8) -> 21102.98
A9: Super-off-peak 10p-6a (kWh) | B9: 7652.88 | C9: 1810.86 | D9: 2263.38 | E9: 2120.78 | F9: 2698.14 | G9: 2110.47 | H9: 1783.44 | I9: 649.47 | J9: =SUM(B9:I9) -> 21089.42
A10: Off-peak (195 basis) (kWh) | B10: -1572.07 | C10: 818.33 | D10: 1078.58 | E10: 805.73 | F10: 413.43 | G10: -193.88 | H10: -448.36 | I10: -366.12 | J10: =SUM(B10:I10) -> 535.64
A11: Off-peak (194 basis) (kWh) | B11: 6080.81 | C11: 2629.19 | D11: 3341.96 | E11: 2926.51 | F11: 3111.57 | G11: 1916.59 | H11: 1335.08 | I11: 283.35 | J11: =SUM(B11:I11) -> 21625.06
A12: On-peak wkdy 3-7p (kWh) | B12: -815.79 | C12: 234.72 | D12: 325.6 | E12: 80.43 | F12: 107.97 | G12: -134.82 | H12: -215.99 | I12: -104.2 | J12: =SUM(B12:I12) -> -522.08
A13: Peak demand (kW) | B13: 16 | C13: 16 | D13: 16 | E13: 16 | F13: 16 | G13: 16 | H13: 16 | I13: 16 | J13: =MAX(B13:I13) -> 16
A15: Rate 580 - Residential, Home Heating
A16: Basic Service | B16: =EffectiveRates!$B$5*B7 -> 91.26 | C16: =EffectiveRates!$C$5*C7 -> 16.74 | D16: =EffectiveRates!$D$5*D7 -> 17.6 | E16: =EffectiveRates!$E$5*E7 -> 15.68 | F16: =EffectiveRates!$F$5*F7 -> 17.36 | G16: =EffectiveRates!$G$5*G7 -> 17.36 | H16: =EffectiveRates!$H$5*H7 -> 16.24 | I16: =EffectiveRates!$I$5*I7 -> 7.84 | J16: =SUM(B16:I16) -> 200.08
A17: Customer Benefit Contribution | B17: =EffectiveRates!$B$8*B13*B7 -> 89.232 | C17: =EffectiveRates!$C$8*C13*C7 -> 16.368 | D17: =EffectiveRates!$D$8*D13*D7 -> 17.9712 | E17: =EffectiveRates!$E$8*E13*E7 -> 16.6656 | F17: =EffectiveRates!$F$8*F13*F7 -> 18.4512 | G17: =EffectiveRates!$G$8*G13*G7 -> 18.4512 | H17: =EffectiveRates!$H$8*H13*H7 -> 17.2608 | I17: =EffectiveRates!$I$8*I13*I7 -> 8.3328 | J17: =SUM(B17:I17) -> 202.7328
A18: Merchant Function Charge | B18: =EffectiveRates!$B$7*B8 -> 9.9298277 | C18: =EffectiveRates!$C$7*C8 -> 5.4013343 | D18: =EffectiveRates!$D$7*D8 -> 6.693297 | E18: =EffectiveRates!$E$7*E8 -> 5.3012352 | F18: =EffectiveRates!$F$7*F8 -> 5.676049 | G18: =EffectiveRates!$G$7*G8 -> 3.1412605 | H18: =EffectiveRates!$H$7*H8 -> 1.9729557 | I18: =EffectiveRates!$I$7*I8 -> 0.31584145 | J18: =SUM(B18:I18) -> 38.431801
A19: Delivery (energy) | B19: =MIN(B8,(250*B7/30))*EffectiveRates!$B$16+MIN(MAX(B8-(250*B7/30),0),(150*B7/30))*EffectiveRates!$B$17+MAX(B8-(250*B7/30)-(150*B7/30),0)*EffectiveRates!$B$18 -> 594.44245 | C19: =MIN(C8,(250*C7/30))*EffectiveRates!$C$16+MIN(MAX(C8-(250*C7/30),0),(150*C7/30))*EffectiveRates!$C$17+MAX(C8-(250*C7/30)-(150*C7/30),0)*EffectiveRates!$C$18 -> 179.67868 | D19: =MIN(D8,(250*D7/30))*EffectiveRates!$D$16+MIN(MAX(D8-(250*D7/30),0),(150*D7/30))*EffectiveRates!$D$17+MAX(D8-(250*D7/30)-(150*D7/30),0)*EffectiveRates!$D$18 -> 230.18319 | E19: =MIN(E8,(250*E7/30))*EffectiveRates!$E$16+MIN(MAX(E8-(250*E7/30),0),(150*E7/30))*EffectiveRates!$E$17+MAX(E8-(250*E7/30)-(150*E7/30),0)*EffectiveRates!$E$18 -> 193.78866 | F19: =MIN(F8,(250*F7/30))*EffectiveRates!$F$16+MIN(MAX(F8-(250*F7/30),0),(150*F7/30))*EffectiveRates!$F$17+MAX(F8-(250*F7/30)-(150*F7/30),0)*EffectiveRates!$F$18 -> 208.14176 | G19: =MIN(G8,(250*G7/30))*EffectiveRates!$G$16+MIN(MAX(G8-(250*G7/30),0),(150*G7/30))*EffectiveRates!$G$17+MAX(G8-(250*G7/30)-(150*G7/30),0)*EffectiveRates!$G$18 -> 124.03221 | H19: =MIN(H8,(250*H7/30))*EffectiveRates!$H$16+MIN(MAX(H8-(250*H7/30),0),(150*H7/30))*EffectiveRates!$H$17+MAX(H8-(250*H7/30)-(150*H7/30),0)*EffectiveRates!$H$18 -> 83.988098 | I19: =MIN(I8,(250*I7/30))*EffectiveRates!$I$16+MIN(MAX(I8-(250*I7/30),0),(150*I7/30))*EffectiveRates!$I$17+MAX(I8-(250*I7/30)-(150*I7/30),0)*EffectiveRates!$I$18 -> 19.06156 | J19: =SUM(B19:I19) -> 1633.3166
A20: Delivery & System subtotal | B20: =B16+B17+B18+B19 -> 784.86427 | C20: =C16+C17+C18+C19 -> 218.18802 | D20: =D16+D17+D18+D19 -> 272.44768 | E20: =E16+E17+E18+E19 -> 231.43549 | F20: =F16+F17+F18+F19 -> 249.62901 | G20: =G16+G17+G18+G19 -> 162.98467 | H20: =H16+H17+H18+H19 -> 119.46185 | I20: =I16+I17+I18+I19 -> 35.550201 | J20: =SUM(B20:I20) -> 2074.5612
A21: Power Supply | B21: =B8*EffectiveRates!$B$15 -> 669.6421 | C21: =C8*EffectiveRates!$C$15 -> 362.86312 | D21: =D8*EffectiveRates!$D$15 -> 468.1677 | E21: =E8*EffectiveRates!$E$15 -> 414.20298 | F21: =F8*EffectiveRates!$F$15 -> 504.20894 | G21: =G8*EffectiveRates!$G$15 -> 295.41925 | H21: =H8*EffectiveRates!$H$15 -> 182.36131 | I21: =I8*EffectiveRates!$I$15 -> 28.696605 | J21: =SUM(B21:I21) -> 2925.562
A22: DER Charge | B22: =EffectiveRates!$B$6*B8 -> 29.241921 | C22: =EffectiveRates!$C$6*C8 -> 15.906156 | D22: =EffectiveRates!$D$6*D8 -> 21.213167 | E22: =EffectiveRates!$E$6*E8 -> 18.083737 | F22: =EffectiveRates!$F$6*F8 -> 19.362314 | G22: =EffectiveRates!$G$6*G8 -> 10.715565 | H22: =EffectiveRates!$H$6*H8 -> 6.7302073 | I22: =EffectiveRates!$I$6*I8 -> 1.0774081 | J22: =SUM(B22:I22) -> 122.33048
A23: Delivery Service Adjustment | B23: =EffectiveRates!$B$9*B8 -> -3.159012 | C23: =EffectiveRates!$C$9*C8 -> -1.718346 | D23: =EffectiveRates!$D$9*D8 -> -2.200536 | E23: =EffectiveRates!$E$9*E8 -> -1.804164 | F23: =EffectiveRates!$F$9*F8 -> -1.931724 | G23: =EffectiveRates!$G$9*G8 -> -1.069062 | H23: =EffectiveRates!$H$9*H8 -> -0.671454 | I23: =EffectiveRates!$I$9*I8 -> -0.10749 | J23: =SUM(B23:I23) -> -12.661788
A24: Revenue Decoupling Adjustment | B24: =EffectiveRates!$B$10*B8 -> -1.579506 | C24: =EffectiveRates!$C$10*C8 -> -0.859173 | D24: =EffectiveRates!$D$10*D8 -> -1.100268 | E24: =EffectiveRates!$E$10*E8 -> -0.902082 | F24: =EffectiveRates!$F$10*F8 -> -0.965862 | G24: =EffectiveRates!$G$10*G8 -> -0.534531 | H24: =EffectiveRates!$H$10*H8 -> -0.335727 | I24: =EffectiveRates!$I$10*I8 -> -0.053745 | J24: =SUM(B24:I24) -> -6.330894
A25: NY State Assessment | B25: =EffectiveRates!$B$11*(B20+B21) -> 3.9271672 | C25: =EffectiveRates!$C$11*(C20+C21) -> 1.5688381 | D25: =EffectiveRates!$D$11*(D20+D21) -> 1.9996615 | E25: =EffectiveRates!$E$11*(E20+E21) -> 1.7432239 | F25: =EffectiveRates!$F$11*(F20+F21) -> 2.0353625 | G25: =EffectiveRates!$G$11*(G20+G21) -> 1.2376906 | H25: =EffectiveRates!$H$11*(H20+H21) -> 0.81492255 | I25: =EffectiveRates!$I$11*(I20+I21) -> 0.17346638 | J25: =SUM(B25:I25) -> 13.500333
A26: Revenue-Based PILOTs | B26: =EffectiveRates!$B$12*(B20+B21) -> 31.271887 | C26: =EffectiveRates!$C$12*(C20+C21) -> 12.4926 | D26: =EffectiveRates!$D$12*(D20+D21) -> 15.923231 | E26: =EffectiveRates!$E$12*(E20+E21) -> 13.881227 | F26: =EffectiveRates!$F$12*(F20+F21) -> 16.207516 | G26: =EffectiveRates!$G$12*(G20+G21) -> 9.8556843 | H26: =EffectiveRates!$H$12*(H20+H21) -> 6.489198 | I26: =EffectiveRates!$I$12*(I20+I21) -> 1.3813063 | J26: =SUM(B26:I26) -> 107.50265
A27: Suffolk Property Tax Adj | B27: =EffectiveRates!$B$13*(B20+B21) -> 33.599097 | C27: =EffectiveRates!$C$13*(C20+C21) -> 13.422281 | D27: =EffectiveRates!$D$13*(D20+D21) -> 17.108215 | E27: =EffectiveRates!$E$13*(E20+E21) -> 14.914249 | F27: =EffectiveRates!$F$13*(F20+F21) -> 17.413657 | G27: =EffectiveRates!$G$13*(G20+G21) -> 10.589131 | H27: =EffectiveRates!$H$13*(H20+H21) -> 6.9721151 | I27: =EffectiveRates!$I$13*(I20+I21) -> 1.4841012 | J27: =SUM(B27:I27) -> 115.50285
A28: Sales Tax | B28: =EffectiveRates!$B$14*(B20+B21+B22+B23+B24+B25+B26+B27) -> 38.695198 | C28: =EffectiveRates!$C$14*(C20+C21+C22+C23+C24+C25+C26+C27) -> 15.546587 | D28: =EffectiveRates!$D$14*(D20+D21+D22+D23+D24+D25+D26+D27) -> 19.838971 | E28: =EffectiveRates!$E$14*(E20+E21+E22+E23+E24+E25+E26+E27) -> 17.288867 | F28: =EffectiveRates!$F$14*(F20+F21+F22+F23+F24+F25+F26+F27) -> 20.14898 | G28: =EffectiveRates!$G$14*(G20+G21+G22+G23+G24+G25+G26+G27) -> 12.22996 | H28: =EffectiveRates!$H$14*(H20+H21+H22+H23+H24+H25+H26+H27) -> 8.0455607 | I28: =EffectiveRates!$I$14*(I20+I21+I22+I23+I24+I25+I26+I27) -> 1.7050463 | J28: =SUM(B28:I28) -> 133.49917
A29: TOTAL CHARGES | B29: =(B20+B21+B22+B23+B24+B25+B26+B27)+B28 -> 1586.5031 | C29: =(C20+C21+C22+C23+C24+C25+C26+C27)+C28 -> 637.41009 | D29: =(D20+D21+D22+D23+D24+D25+D26+D27)+D28 -> 813.39783 | E29: =(E20+E21+E22+E23+E24+E25+E26+E27)+E28 -> 708.84353 | F29: =(F20+F21+F22+F23+F24+F25+F26+F27)+F28 -> 826.10819 | G29: =(G20+G21+G22+G23+G24+G25+G26+G27)+G28 -> 501.42836 | H29: =(H20+H21+H22+H23+H24+H25+H26+H27)+H28 -> 329.86799 | I29: =(I20+I21+I22+I23+I24+I25+I26+I27)+I28 -> 69.9069 | J29: =SUM(B29:I29) -> 5473.466
A31: Rate 180 - Residential (standard)
A32: Basic Service | B32: =EffectiveRates!$B$5*B7 -> 91.26 | C32: =EffectiveRates!$C$5*C7 -> 16.74 | D32: =EffectiveRates!$D$5*D7 -> 17.6 | E32: =EffectiveRates!$E$5*E7 -> 15.68 | F32: =EffectiveRates!$F$5*F7 -> 17.36 | G32: =EffectiveRates!$G$5*G7 -> 17.36 | H32: =EffectiveRates!$H$5*H7 -> 16.24 | I32: =EffectiveRates!$I$5*I7 -> 7.84 | J32: =SUM(B32:I32) -> 200.08
A33: Customer Benefit Contribution | B33: =EffectiveRates!$B$8*B13*B7 -> 89.232 | C33: =EffectiveRates!$C$8*C13*C7 -> 16.368 | D33: =EffectiveRates!$D$8*D13*D7 -> 17.9712 | E33: =EffectiveRates!$E$8*E13*E7 -> 16.6656 | F33: =EffectiveRates!$F$8*F13*F7 -> 18.4512 | G33: =EffectiveRates!$G$8*G13*G7 -> 18.4512 | H33: =EffectiveRates!$H$8*H13*H7 -> 17.2608 | I33: =EffectiveRates!$I$8*I13*I7 -> 8.3328 | J33: =SUM(B33:I33) -> 202.7328
A34: Merchant Function Charge | B34: =EffectiveRates!$B$7*B8 -> 9.9298277 | C34: =EffectiveRates!$C$7*C8 -> 5.4013343 | D34: =EffectiveRates!$D$7*D8 -> 6.693297 | E34: =EffectiveRates!$E$7*E8 -> 5.3012352 | F34: =EffectiveRates!$F$7*F8 -> 5.676049 | G34: =EffectiveRates!$G$7*G8 -> 3.1412605 | H34: =EffectiveRates!$H$7*H8 -> 1.9729557 | I34: =EffectiveRates!$I$7*I8 -> 0.31584145 | J34: =SUM(B34:I34) -> 38.431801
A35: Delivery (energy) | B35: =MIN(B8,(250*B7/30))*EffectiveRates!$B$19+MAX(B8-(250*B7/30),0)*EffectiveRates!$B$20 -> 632.97095 | C35: =MIN(C8,(250*C7/30))*EffectiveRates!$C$19+MAX(C8-(250*C7/30),0)*EffectiveRates!$C$20 -> 292.40521 | D35: =MIN(D8,(250*D7/30))*EffectiveRates!$D$19+MAX(D8-(250*D7/30),0)*EffectiveRates!$D$20 -> 382.34313 | E35: =MIN(E8,(250*E7/30))*EffectiveRates!$E$19+MAX(E8-(250*E7/30),0)*EffectiveRates!$E$20 -> 319.93842 | F35: =MIN(F8,(250*F7/30))*EffectiveRates!$F$19+MAX(F8-(250*F7/30),0)*EffectiveRates!$F$20 -> 342.55906 | G35: =MIN(G8,(250*G7/30))*EffectiveRates!$G$19+MAX(G8-(250*G7/30),0)*EffectiveRates!$G$20 -> 189.58033 | H35: =MIN(H8,(250*H7/30))*EffectiveRates!$H$19+MAX(H8-(250*H7/30),0)*EffectiveRates!$H$20 -> 119.07118 | I35: =MIN(I8,(250*I7/30))*EffectiveRates!$I$19+MAX(I8-(250*I7/30),0)*EffectiveRates!$I$20 -> 19.06156 | J35: =SUM(B35:I35) -> 2297.9298
A36: Delivery & System subtotal | B36: =B32+B33+B34+B35 -> 823.39278 | C36: =C32+C33+C34+C35 -> 330.91455 | D36: =D32+D33+D34+D35 -> 424.60763 | E36: =E32+E33+E34+E35 -> 357.58525 | F36: =F32+F33+F34+F35 -> 384.04631 | G36: =G32+G33+G34+G35 -> 228.53279 | H36: =H32+H33+H34+H35 -> 154.54493 | I36: =I32+I33+I34+I35 -> 35.550201 | J36: =SUM(B36:I36) -> 2739.1744
A37: Power Supply | B37: =B8*EffectiveRates!$B$15 -> 669.6421 | C37: =C8*EffectiveRates!$C$15 -> 362.86312 | D37: =D8*EffectiveRates!$D$15 -> 468.1677 | E37: =E8*EffectiveRates!$E$15 -> 414.20298 | F37: =F8*EffectiveRates!$F$15 -> 504.20894 | G37: =G8*EffectiveRates!$G$15 -> 295.41925 | H37: =H8*EffectiveRates!$H$15 -> 182.36131 | I37: =I8*EffectiveRates!$I$15 -> 28.696605 | J37: =SUM(B37:I37) -> 2925.562
A38: DER Charge | B38: =EffectiveRates!$B$6*B8 -> 29.241921 | C38: =EffectiveRates!$C$6*C8 -> 15.906156 | D38: =EffectiveRates!$D$6*D8 -> 21.213167 | E38: =EffectiveRates!$E$6*E8 -> 18.083737 | F38: =EffectiveRates!$F$6*F8 -> 19.362314 | G38: =EffectiveRates!$G$6*G8 -> 10.715565 | H38: =EffectiveRates!$H$6*H8 -> 6.7302073 | I38: =EffectiveRates!$I$6*I8 -> 1.0774081 | J38: =SUM(B38:I38) -> 122.33048
A39: Delivery Service Adjustment | B39: =EffectiveRates!$B$9*B8 -> -3.159012 | C39: =EffectiveRates!$C$9*C8 -> -1.718346 | D39: =EffectiveRates!$D$9*D8 -> -2.200536 | E39: =EffectiveRates!$E$9*E8 -> -1.804164 | F39: =EffectiveRates!$F$9*F8 -> -1.931724 | G39: =EffectiveRates!$G$9*G8 -> -1.069062 | H39: =EffectiveRates!$H$9*H8 -> -0.671454 | I39: =EffectiveRates!$I$9*I8 -> -0.10749 | J39: =SUM(B39:I39) -> -12.661788
A40: Revenue Decoupling Adjustment | B40: =EffectiveRates!$B$10*B8 -> -1.579506 | C40: =EffectiveRates!$C$10*C8 -> -0.859173 | D40: =EffectiveRates!$D$10*D8 -> -1.100268 | E40: =EffectiveRates!$E$10*E8 -> -0.902082 | F40: =EffectiveRates!$F$10*F8 -> -0.965862 | G40: =EffectiveRates!$G$10*G8 -> -0.534531 | H40: =EffectiveRates!$H$10*H8 -> -0.335727 | I40: =EffectiveRates!$I$10*I8 -> -0.053745 | J40: =SUM(B40:I40) -> -6.330894
A41: NY State Assessment | B41: =EffectiveRates!$B$11*(B36+B37) -> 4.0311942 | C41: =EffectiveRates!$C$11*(C36+C37) -> 1.8731997 | D41: =EffectiveRates!$D$11*(D36+D37) -> 2.4104934 | E41: =EffectiveRates!$E$11*(E36+E37) -> 2.0838282 | F41: =EffectiveRates!$F$11*(F36+F37) -> 2.3982892 | G41: =EffectiveRates!$G$11*(G36+G37) -> 1.4146705 | H41: =EffectiveRates!$H$11*(H36+H37) -> 0.90964686 | I41: =EffectiveRates!$I$11*(I36+I37) -> 0.17346638 | J41: =SUM(B41:I41) -> 15.294788
A42: Revenue-Based PILOTs | B42: =EffectiveRates!$B$12*(B36+B37) -> 32.10025 | C42: =EffectiveRates!$C$12*(C36+C37) -> 14.91622 | D42: =EffectiveRates!$D$12*(D36+D37) -> 19.19467 | E42: =EffectiveRates!$E$12*(E36+E37) -> 16.593447 | F42: =EffectiveRates!$F$12*(F36+F37) -> 19.097488 | G42: =EffectiveRates!$G$12*(G36+G37) -> 11.264969 | H42: =EffectiveRates!$H$12*(H36+H37) -> 7.2434842 | I42: =EffectiveRates!$I$12*(I36+I37) -> 1.3813063 | J42: =SUM(B42:I42) -> 121.79183
A43: Suffolk Property Tax Adj | B43: =EffectiveRates!$B$13*(B36+B37) -> 34.489106 | C43: =EffectiveRates!$C$13*(C36+C37) -> 16.026264 | D43: =EffectiveRates!$D$13*(D36+D37) -> 20.62311 | E43: =EffectiveRates!$E$13*(E36+E37) -> 17.828308 | F43: =EffectiveRates!$F$13*(F36+F37) -> 20.518696 | G43: =EffectiveRates!$G$13*(G36+G37) -> 12.103292 | H43: =EffectiveRates!$H$13*(H36+H37) -> 7.7825342 | I43: =EffectiveRates!$I$13*(I36+I37) -> 1.4841012 | J43: =SUM(B43:I43) -> 130.85541
A44: Sales Tax | B44: =EffectiveRates!$B$14*(B36+B37+B38+B39+B40+B41+B42+B43) -> 39.703971 | C44: =EffectiveRates!$C$14*(C36+C37+C38+C39+C40+C41+C42+C43) -> 18.49805 | D44: =EffectiveRates!$D$14*(D36+D37+D38+D39+D40+D41+D42+D43) -> 23.822899 | E44: =EffectiveRates!$E$14*(E36+E37+E38+E39+E40+E41+E42+E43) -> 20.591783 | F44: =EffectiveRates!$F$14*(F36+F37+F38+F39+F40+F41+F42+F43) -> 23.668361 | G44: =EffectiveRates!$G$14*(G36+G37+G38+G39+G40+G41+G42+G43) -> 13.946173 | H44: =EffectiveRates!$H$14*(H36+H37+H38+H39+H40+H41+H42+H43) -> 8.9641234 | I44: =EffectiveRates!$I$14*(I36+I37+I38+I39+I40+I41+I42+I43) -> 1.7050463 | J44: =SUM(B44:I44) -> 150.90041
A45: TOTAL CHARGES | B45: =(B36+B37+B38+B39+B40+B41+B42+B43)+B44 -> 1627.8628 | C45: =(C36+C37+C38+C39+C40+C41+C42+C43)+C44 -> 758.42004 | D45: =(D36+D37+D38+D39+D40+D41+D42+D43)+D44 -> 976.73886 | E45: =(E36+E37+E38+E39+E40+E41+E42+E43)+E44 -> 844.26309 | F45: =(F36+F37+F38+F39+F40+F41+F42+F43)+F44 -> 970.40281 | G45: =(G36+G37+G38+G39+G40+G41+G42+G43)+G44 -> 571.79311 | H45: =(H36+H37+H38+H39+H40+H41+H42+H43)+H44 -> 367.52906 | I45: =(I36+I37+I38+I39+I40+I41+I42+I43)+I44 -> 69.9069 | J45: =SUM(B45:I45) -> 6186.9167
A47: Rate 194 - Time-of-Day, Off-Peak
A48: Basic Service | B48: =EffectiveRates!$B$5*B7 -> 91.26 | C48: =EffectiveRates!$C$5*C7 -> 16.74 | D48: =EffectiveRates!$D$5*D7 -> 17.6 | E48: =EffectiveRates!$E$5*E7 -> 15.68 | F48: =EffectiveRates!$F$5*F7 -> 17.36 | G48: =EffectiveRates!$G$5*G7 -> 17.36 | H48: =EffectiveRates!$H$5*H7 -> 16.24 | I48: =EffectiveRates!$I$5*I7 -> 7.84 | J48: =SUM(B48:I48) -> 200.08
A49: Customer Benefit Contribution | B49: =EffectiveRates!$B$8*B13*B7 -> 89.232 | C49: =EffectiveRates!$C$8*C13*C7 -> 16.368 | D49: =EffectiveRates!$D$8*D13*D7 -> 17.9712 | E49: =EffectiveRates!$E$8*E13*E7 -> 16.6656 | F49: =EffectiveRates!$F$8*F13*F7 -> 18.4512 | G49: =EffectiveRates!$G$8*G13*G7 -> 18.4512 | H49: =EffectiveRates!$H$8*H13*H7 -> 17.2608 | I49: =EffectiveRates!$I$8*I13*I7 -> 8.3328 | J49: =SUM(B49:I49) -> 202.7328
A50: Merchant Function Charge | B50: =EffectiveRates!$B$7*B8 -> 9.9298277 | C50: =EffectiveRates!$C$7*C8 -> 5.4013343 | D50: =EffectiveRates!$D$7*D8 -> 6.693297 | E50: =EffectiveRates!$E$7*E8 -> 5.3012352 | F50: =EffectiveRates!$F$7*F8 -> 5.676049 | G50: =EffectiveRates!$G$7*G8 -> 3.1412605 | H50: =EffectiveRates!$H$7*H8 -> 1.9729557 | I50: =EffectiveRates!$I$7*I8 -> 0.31584145 | J50: =SUM(B50:I50) -> 38.431801
A51: Delivery (energy) | B51: =B12*EffectiveRates!$B$22+B11*EffectiveRates!$B$21 -> 463.5695 | C51: =C12*EffectiveRates!$C$22+C11*EffectiveRates!$C$21 -> 288.49647 | D51: =D12*EffectiveRates!$D$22+D11*EffectiveRates!$D$21 -> 371.84368 | E51: =E12*EffectiveRates!$E$22+E11*EffectiveRates!$E$21 -> 287.03383 | F51: =F12*EffectiveRates!$F$22+F11*EffectiveRates!$F$21 -> 309.4172 | G51: =G12*EffectiveRates!$G$22+G11*EffectiveRates!$G$21 -> 152.63764 | H51: =H12*EffectiveRates!$H$22+H11*EffectiveRates!$H$21 -> 83.314817 | I51: =I12*EffectiveRates!$I$22+I11*EffectiveRates!$I$21 -> 6.681515 | J51: =SUM(B51:I51) -> 1962.9947
A52: Delivery & System subtotal | B52: =B48+B49+B50+B51 -> 653.99133 | C52: =C48+C49+C50+C51 -> 327.00581 | D52: =D48+D49+D50+D51 -> 414.10818 | E52: =E48+E49+E50+E51 -> 324.68067 | F52: =F48+F49+F50+F51 -> 350.90445 | G52: =G48+G49+G50+G51 -> 191.5901 | H52: =H48+H49+H50+H51 -> 118.78857 | I52: =I48+I49+I50+I51 -> 23.170156 | J52: =SUM(B52:I52) -> 2404.2393
A53: Power Supply | B53: =EffectiveRates!$B$15*(B11*EffectiveRates!$B$23+B12*EffectiveRates!$B$24) -> 434.24716 | C53: =EffectiveRates!$C$15*(C11*EffectiveRates!$C$23+C12*EffectiveRates!$C$24) -> 339.95669 | D53: =EffectiveRates!$D$15*(D11*EffectiveRates!$D$23+D12*EffectiveRates!$D$24) -> 442.77756 | E53: =EffectiveRates!$E$15*(E11*EffectiveRates!$E$23+E12*EffectiveRates!$E$24) -> 358.23569 | F53: =EffectiveRates!$F$15*(F11*EffectiveRates!$F$23+F12*EffectiveRates!$F$24) -> 440.54285 | G53: =EffectiveRates!$G$15*(G11*EffectiveRates!$G$23+G12*EffectiveRates!$G$24) -> 216.04928 | H53: =EffectiveRates!$H$15*(H11*EffectiveRates!$H$23+H12*EffectiveRates!$H$24) -> 105.46346 | I53: =EffectiveRates!$I$15*(I11*EffectiveRates!$I$23+I12*EffectiveRates!$I$24) -> 2.0531648 | J53: =SUM(B53:I53) -> 2339.3259
A54: DER Charge | B54: =EffectiveRates!$B$6*B8 -> 29.241921 | C54: =EffectiveRates!$C$6*C8 -> 15.906156 | D54: =EffectiveRates!$D$6*D8 -> 21.213167 | E54: =EffectiveRates!$E$6*E8 -> 18.083737 | F54: =EffectiveRates!$F$6*F8 -> 19.362314 | G54: =EffectiveRates!$G$6*G8 -> 10.715565 | H54: =EffectiveRates!$H$6*H8 -> 6.7302073 | I54: =EffectiveRates!$I$6*I8 -> 1.0774081 | J54: =SUM(B54:I54) -> 122.33048
A55: Delivery Service Adjustment | B55: =EffectiveRates!$B$9*B8 -> -3.159012 | C55: =EffectiveRates!$C$9*C8 -> -1.718346 | D55: =EffectiveRates!$D$9*D8 -> -2.200536 | E55: =EffectiveRates!$E$9*E8 -> -1.804164 | F55: =EffectiveRates!$F$9*F8 -> -1.931724 | G55: =EffectiveRates!$G$9*G8 -> -1.069062 | H55: =EffectiveRates!$H$9*H8 -> -0.671454 | I55: =EffectiveRates!$I$9*I8 -> -0.10749 | J55: =SUM(B55:I55) -> -12.661788
A56: Revenue Decoupling Adjustment | B56: =EffectiveRates!$B$10*B8 -> -1.579506 | C56: =EffectiveRates!$C$10*C8 -> -0.859173 | D56: =EffectiveRates!$D$10*D8 -> -1.100268 | E56: =EffectiveRates!$E$10*E8 -> -0.902082 | F56: =EffectiveRates!$F$10*F8 -> -0.965862 | G56: =EffectiveRates!$G$10*G8 -> -0.534531 | H56: =EffectiveRates!$H$10*H8 -> -0.335727 | I56: =EffectiveRates!$I$10*I8 -> -0.053745 | J56: =SUM(B56:I56) -> -6.330894
A57: NY State Assessment | B57: =EffectiveRates!$B$11*(B52+B53) -> 2.9382439 | C57: =EffectiveRates!$C$11*(C52+C53) -> 1.8007987 | D57: =EffectiveRates!$D$11*(D52+D53) -> 2.3135915 | E57: =EffectiveRates!$E$11*(E52+E53) -> 1.8438742 | F57: =EffectiveRates!$F$11*(F52+F53) -> 2.1369077 | G57: =EffectiveRates!$G$11*(G52+G53) -> 1.1006263 | H57: =EffectiveRates!$H$11*(H52+H53) -> 0.60548048 | I57: =EffectiveRates!$I$11*(I52+I53) -> 0.068102967 | J57: =SUM(B57:I57) -> 12.807626
A58: Revenue-Based PILOTs | B58: =EffectiveRates!$B$12*(B52+B53) -> 23.397128 | C58: =EffectiveRates!$C$12*(C52+C53) -> 14.339694 | D58: =EffectiveRates!$D$12*(D52+D53) -> 18.423043 | E58: =EffectiveRates!$E$12*(E52+E53) -> 14.682702 | F58: =EffectiveRates!$F$12*(F52+F53) -> 17.016117 | G58: =EffectiveRates!$G$12*(G52+G53) -> 8.7642468 | H58: =EffectiveRates!$H$12*(H52+H53) -> 4.8214186 | I58: =EffectiveRates!$I$12*(I52+I53) -> 0.54230141 | J58: =SUM(B58:I58) -> 101.98665
A59: Suffolk Property Tax Adj | B59: =EffectiveRates!$B$13*(B52+B53) -> 25.138309 | C59: =EffectiveRates!$C$13*(C52+C53) -> 15.406834 | D59: =EffectiveRates!$D$13*(D52+D53) -> 19.794061 | E59: =EffectiveRates!$E$13*(E52+E53) -> 15.775368 | F59: =EffectiveRates!$F$13*(F52+F53) -> 18.282433 | G59: =EffectiveRates!$G$13*(G52+G53) -> 9.4164698 | H59: =EffectiveRates!$H$13*(H52+H53) -> 5.1802219 | I59: =EffectiveRates!$I$13*(I52+I53) -> 0.58265872 | J59: =SUM(B59:I59) -> 109.57635
A60: Sales Tax | B60: =EffectiveRates!$B$14*(B52+B53+B54+B55+B56+B57+B58+B59) -> 29.105389 | C60: =EffectiveRates!$C$14*(C52+C53+C54+C55+C56+C57+C58+C59) -> 17.795962 | D60: =EffectiveRates!$D$14*(D52+D53+D54+D55+D56+D57+D58+D59) -> 22.88322 | E60: =EffectiveRates!$E$14*(E52+E53+E54+E55+E56+E57+E58+E59) -> 18.264895 | F60: =EffectiveRates!$F$14*(F52+F53+F54+F55+F56+F57+F58+F59) -> 21.133687 | G60: =EffectiveRates!$G$14*(G52+G53+G54+G55+G56+G57+G58+G59) -> 10.900818 | H60: =EffectiveRates!$H$14*(H52+H53+H54+H55+H56+H57+H58+H59) -> 6.0145544 | I60: =EffectiveRates!$I$14*(I52+I53+I54+I55+I56+I57+I58+I59) -> 0.68331394 | J60: =SUM(B60:I60) -> 126.78184
A61: TOTAL CHARGES | B61: =(B52+B53+B54+B55+B56+B57+B58+B59)+B60 -> 1193.321 | C61: =(C52+C53+C54+C55+C56+C57+C58+C59)+C60 -> 729.63442 | D61: =(D52+D53+D54+D55+D56+D57+D58+D59)+D60 -> 938.21202 | E61: =(E52+E53+E54+E55+E56+E57+E58+E59)+E60 -> 748.86068 | F61: =(F52+F53+F54+F55+F56+F57+F58+F59)+F60 -> 866.48117 | G61: =(G52+G53+G54+G55+G56+G57+G58+G59)+G60 -> 446.93352 | H61: =(H52+H53+H54+H55+H56+H57+H58+H59)+H60 -> 246.59673 | I61: =(I52+I53+I54+I55+I56+I57+I58+I59)+I60 -> 28.015871 | J61: =SUM(B61:I61) -> 5198.0554
A63: Rate 195 - Time-of-Day, Super Off-Peak
A64: Basic Service | B64: =EffectiveRates!$B$5*B7 -> 91.26 | C64: =EffectiveRates!$C$5*C7 -> 16.74 | D64: =EffectiveRates!$D$5*D7 -> 17.6 | E64: =EffectiveRates!$E$5*E7 -> 15.68 | F64: =EffectiveRates!$F$5*F7 -> 17.36 | G64: =EffectiveRates!$G$5*G7 -> 17.36 | H64: =EffectiveRates!$H$5*H7 -> 16.24 | I64: =EffectiveRates!$I$5*I7 -> 7.84 | J64: =SUM(B64:I64) -> 200.08
A65: Customer Benefit Contribution | B65: =EffectiveRates!$B$8*B13*B7 -> 89.232 | C65: =EffectiveRates!$C$8*C13*C7 -> 16.368 | D65: =EffectiveRates!$D$8*D13*D7 -> 17.9712 | E65: =EffectiveRates!$E$8*E13*E7 -> 16.6656 | F65: =EffectiveRates!$F$8*F13*F7 -> 18.4512 | G65: =EffectiveRates!$G$8*G13*G7 -> 18.4512 | H65: =EffectiveRates!$H$8*H13*H7 -> 17.2608 | I65: =EffectiveRates!$I$8*I13*I7 -> 8.3328 | J65: =SUM(B65:I65) -> 202.7328
A66: Merchant Function Charge | B66: =EffectiveRates!$B$7*B8 -> 9.9298277 | C66: =EffectiveRates!$C$7*C8 -> 5.4013343 | D66: =EffectiveRates!$D$7*D8 -> 6.693297 | E66: =EffectiveRates!$E$7*E8 -> 5.3012352 | F66: =EffectiveRates!$F$7*F8 -> 5.676049 | G66: =EffectiveRates!$G$7*G8 -> 3.1412605 | H66: =EffectiveRates!$H$7*H8 -> 1.9729557 | I66: =EffectiveRates!$I$7*I8 -> 0.31584145 | J66: =SUM(B66:I66) -> 38.431801
A67: Delivery (energy) | B67: =B9*EffectiveRates!$B$25+B10*EffectiveRates!$B$26+B12*EffectiveRates!$B$27 -> -83.449377 | C67: =C9*EffectiveRates!$C$25+C10*EffectiveRates!$C$26+C12*EffectiveRates!$C$27 -> 214.78324 | D67: =D9*EffectiveRates!$D$25+D10*EffectiveRates!$D$26+D12*EffectiveRates!$D$27 -> 281.49858 | E67: =E9*EffectiveRates!$E$25+E10*EffectiveRates!$E$26+E12*EffectiveRates!$E$27 -> 189.91234 | F67: =F9*EffectiveRates!$F$25+F10*EffectiveRates!$F$26+F12*EffectiveRates!$F$27 -> 186.16863 | G67: =G9*EffectiveRates!$G$25+G10*EffectiveRates!$G$26+G12*EffectiveRates!$G$27 -> 44.063618 | H67: =H9*EffectiveRates!$H$25+H10*EffectiveRates!$H$26+H12*EffectiveRates!$H$27 -> -14.099404 | I67: =I9*EffectiveRates!$I$25+I10*EffectiveRates!$I$26+I12*EffectiveRates!$I$27 -> -30.211198 | J67: =SUM(B67:I67) -> 788.66642
A68: Delivery & System subtotal | B68: =B64+B65+B66+B67 -> 106.97245 | C68: =C64+C65+C66+C67 -> 253.29257 | D68: =D64+D65+D66+D67 -> 323.76308 | E68: =E64+E65+E66+E67 -> 227.55917 | F68: =F64+F65+F66+F67 -> 227.65588 | G68: =G64+G65+G66+G67 -> 83.016079 | H68: =H64+H65+H66+H67 -> 21.374352 | I68: =I64+I65+I66+I67 -> -13.722557 | J68: =SUM(B68:I68) -> 1229.911
A69: Power Supply | B69: =EffectiveRates!$B$15*(B9*EffectiveRates!$B$28+B10*EffectiveRates!$B$29+B12*EffectiveRates!$B$30) -> 196.77806 | C69: =EffectiveRates!$C$15*(C9*EffectiveRates!$C$28+C10*EffectiveRates!$C$29+C12*EffectiveRates!$C$30) -> 299.89891 | D69: =EffectiveRates!$D$15*(D9*EffectiveRates!$D$28+D10*EffectiveRates!$D$29+D12*EffectiveRates!$D$30) -> 392.86501 | E69: =EffectiveRates!$E$15*(E9*EffectiveRates!$E$28+E10*EffectiveRates!$E$29+E12*EffectiveRates!$E$30) -> 308.08233 | F69: =EffectiveRates!$F$15*(F9*EffectiveRates!$F$28+F10*EffectiveRates!$F$29+F12*EffectiveRates!$F$30) -> 351.56925 | G69: =EffectiveRates!$G$15*(G9*EffectiveRates!$G$28+G10*EffectiveRates!$G$29+G12*EffectiveRates!$G$30) -> 133.79617 | H69: =EffectiveRates!$H$15*(H9*EffectiveRates!$H$28+H10*EffectiveRates!$H$29+H12*EffectiveRates!$H$30) -> 32.01461 | I69: =EffectiveRates!$I$15*(I9*EffectiveRates!$I$28+I10*EffectiveRates!$I$29+I12*EffectiveRates!$I$30) -> -29.086962 | J69: =SUM(B69:I69) -> 1685.9174
A70: DER Charge | B70: =EffectiveRates!$B$6*B8 -> 29.241921 | C70: =EffectiveRates!$C$6*C8 -> 15.906156 | D70: =EffectiveRates!$D$6*D8 -> 21.213167 | E70: =EffectiveRates!$E$6*E8 -> 18.083737 | F70: =EffectiveRates!$F$6*F8 -> 19.362314 | G70: =EffectiveRates!$G$6*G8 -> 10.715565 | H70: =EffectiveRates!$H$6*H8 -> 6.7302073 | I70: =EffectiveRates!$I$6*I8 -> 1.0774081 | J70: =SUM(B70:I70) -> 122.33048
A71: Delivery Service Adjustment | B71: =EffectiveRates!$B$9*B8 -> -3.159012 | C71: =EffectiveRates!$C$9*C8 -> -1.718346 | D71: =EffectiveRates!$D$9*D8 -> -2.200536 | E71: =EffectiveRates!$E$9*E8 -> -1.804164 | F71: =EffectiveRates!$F$9*F8 -> -1.931724 | G71: =EffectiveRates!$G$9*G8 -> -1.069062 | H71: =EffectiveRates!$H$9*H8 -> -0.671454 | I71: =EffectiveRates!$I$9*I8 -> -0.10749 | J71: =SUM(B71:I71) -> -12.661788
A72: Revenue Decoupling Adjustment | B72: =EffectiveRates!$B$10*B8 -> -1.579506 | C72: =EffectiveRates!$C$10*C8 -> -0.859173 | D72: =EffectiveRates!$D$10*D8 -> -1.100268 | E72: =EffectiveRates!$E$10*E8 -> -0.902082 | F72: =EffectiveRates!$F$10*F8 -> -0.965862 | G72: =EffectiveRates!$G$10*G8 -> -0.534531 | H72: =EffectiveRates!$H$10*H8 -> -0.335727 | I72: =EffectiveRates!$I$10*I8 -> -0.053745 | J72: =SUM(B72:I72) -> -6.330894
A73: NY State Assessment | B73: =EffectiveRates!$B$11*(B68+B69) -> 0.82012637 | C73: =EffectiveRates!$C$11*(C68+C69) -> 1.493617 | D73: =EffectiveRates!$D$11*(D68+D69) -> 1.9348958 | E73: =EffectiveRates!$E$11*(E68+E69) -> 1.4462321 | F73: =EffectiveRates!$F$11*(F68+F69) -> 1.5639078 | G73: =EffectiveRates!$G$11*(G68+G69) -> 0.58539306 | H73: =EffectiveRates!$H$11*(H68+H69) -> 0.1441502 | I73: =EffectiveRates!$I$11*(I68+I69) -> -0.1155857 | J73: =SUM(B73:I73) -> 7.8727367
A74: Revenue-Based PILOTs | B74: =EffectiveRates!$B$12*(B68+B69) -> 6.5306359 | C74: =EffectiveRates!$C$12*(C68+C69) -> 11.893617 | D74: =EffectiveRates!$D$12*(D68+D69) -> 15.407504 | E74: =EffectiveRates!$E$12*(E68+E69) -> 11.516292 | F74: =EffectiveRates!$F$12*(F68+F69) -> 12.45334 | G74: =EffectiveRates!$G$12*(G68+G69) -> 4.6614632 | H74: =EffectiveRates!$H$12*(H68+H69) -> 1.1478627 | I74: =EffectiveRates!$I$12*(I68+I69) -> -0.92040466 | J74: =SUM(B74:I74) -> 62.69031
A75: Suffolk Property Tax Adj | B75: =EffectiveRates!$B$13*(B68+B69) -> 7.0166367 | C75: =EffectiveRates!$C$13*(C68+C69) -> 12.778723 | D75: =EffectiveRates!$D$13*(D68+D69) -> 16.554109 | E75: =EffectiveRates!$E$13*(E68+E69) -> 12.373319 | F75: =EffectiveRates!$F$13*(F68+F69) -> 13.3801 | G75: =EffectiveRates!$G$13*(G68+G69) -> 5.0083628 | H75: =EffectiveRates!$H$13*(H68+H69) -> 1.233285 | I75: =EffectiveRates!$I$13*(I68+I69) -> -0.98889989 | J75: =SUM(B75:I75) -> 67.355636
A76: Sales Tax | B76: =EffectiveRates!$B$14*(B68+B69+B70+B71+B72+B73+B74+B75) -> 8.5655327 | C76: =EffectiveRates!$C$14*(C68+C69+C70+C71+C72+C73+C74+C75) -> 14.817152 | D76: =EffectiveRates!$D$14*(D68+D69+D70+D71+D72+D73+D74+D75) -> 19.210924 | E76: =EffectiveRates!$E$14*(E68+E69+E70+E71+E72+E73+E74+E75) -> 14.408871 | F76: =EffectiveRates!$F$14*(F68+F69+F70+F71+F72+F73+F74+F75) -> 15.57718 | G76: =EffectiveRates!$G$14*(G68+G69+G70+G71+G72+G73+G74+G75) -> 5.9044859 | H76: =EffectiveRates!$H$14*(H68+H69+H70+H71+H72+H73+H74+H75) -> 1.5409321 | I76: =EffectiveRates!$I$14*(I68+I69+I70+I71+I72+I73+I74+I75) -> -1.0979559 | J76: =SUM(B76:I76) -> 78.927122
A77: TOTAL CHARGES | B77: =(B68+B69+B70+B71+B72+B73+B74+B75)+B76 -> 351.18684 | C77: =(C68+C69+C70+C71+C72+C73+C74+C75)+C76 -> 607.50323 | D77: =(D68+D69+D70+D71+D72+D73+D74+D75)+D76 -> 787.64788 | E77: =(E68+E69+E70+E71+E72+E73+E74+E75)+E76 -> 590.76371 | F77: =(F68+F69+F70+F71+F72+F73+F74+F75)+F76 -> 638.66438 | G77: =(G68+G69+G70+G71+G72+G73+G74+G75)+G76 -> 242.08392 | H77: =(H68+H69+H70+H71+H72+H73+H74+H75)+H76 -> 63.178218 | I77: =(I68+I69+I70+I71+I72+I73+I74+I75)+I76 -> -45.016192 | J77: =SUM(B77:I77) -> 3236.012
A80: RATE COMPARISON - total bill ($)
A81: Rate plan | B81: Cycle 1 | C81: Cycle 2 | D81: Cycle 3 | E81: Cycle 4 | F81: Cycle 5 | G81: Cycle 6 | H81: Cycle 7 | I81: Cycle 8 | J81: TOTAL
A82: Rate 580 - Residential, Home Heating | B82: =B29 -> 1586.5031 | C82: =C29 -> 637.41009 | D82: =D29 -> 813.39783 | E82: =E29 -> 708.84353 | F82: =F29 -> 826.10819 | G82: =G29 -> 501.42836 | H82: =H29 -> 329.86799 | I82: =I29 -> 69.9069 | J82: =J29 -> 5473.466
A83: Rate 180 - Residential (standard) | B83: =B45 -> 1627.8628 | C83: =C45 -> 758.42004 | D83: =D45 -> 976.73886 | E83: =E45 -> 844.26309 | F83: =F45 -> 970.40281 | G83: =G45 -> 571.79311 | H83: =H45 -> 367.52906 | I83: =I45 -> 69.9069 | J83: =J45 -> 6186.9167
A84: Rate 194 - Time-of-Day, Off-Peak | B84: =B61 -> 1193.321 | C84: =C61 -> 729.63442 | D84: =D61 -> 938.21202 | E84: =E61 -> 748.86068 | F84: =F61 -> 866.48117 | G84: =G61 -> 446.93352 | H84: =H61 -> 246.59673 | I84: =I61 -> 28.015871 | J84: =J61 -> 5198.0554
A85: Rate 195 - Time-of-Day, Super Off-Peak | B85: =B77 -> 351.18684 | C85: =C77 -> 607.50323 | D85: =D77 -> 787.64788 | E85: =E77 -> 590.76371 | F85: =F77 -> 638.66438 | G85: =G77 -> 242.08392 | H85: =H77 -> 63.178218 | I85: =I77 -> -45.016192 | J85: =J77 -> 3236.012
A86: Lowest-cost plan | B86: =INDEX({"580";"180";"194";"195"},MATCH(MIN(B82:B85),B82:B85,0)) -> 195 | C86: =INDEX({"580";"180";"194";"195"},MATCH(MIN(C82:C85),C82:C85,0)) -> 195 | D86: =INDEX({"580";"180";"194";"195"},MATCH(MIN(D82:D85),D82:D85,0)) -> 195 | E86: =INDEX({"580";"180";"194";"195"},MATCH(MIN(E82:E85),E82:E85,0)) -> 195 | F86: =INDEX({"580";"180";"194";"195"},MATCH(MIN(F82:F85),F82:F85,0)) -> 195 | G86: =INDEX({"580";"180";"194";"195"},MATCH(MIN(G82:G85),G82:G85,0)) -> 195 | H86: =INDEX({"580";"180";"194";"195"},MATCH(MIN(H82:H85),H82:H85,0)) -> 195 | I86: =INDEX({"580";"180";"194";"195"},MATCH(MIN(I82:I85),I82:I85,0)) -> 195 | J86: =INDEX({"580";"180";"194";"195"},MATCH(MIN(J82:J85),J82:J85,0)) -> 195
A88: Date-matched estimate: each cycle uses day-weighted rates from the Rates schedule (blends rate changes & seasons). Suffolk Prop Tax applies to Suffolk County only. Yellow cells on Rates = estimated/stale; refresh with --refresh while online.

Sheet Rates
A1: PSEG LI MONTHLY RATE SCHEDULE (source)
A2: Blue = inputs. 'flag' shows data provenance. Dashboard uses date-weighted blends of these per billing cycle.
A4: Month | B4: flag | C4: Supply PSC | D4: Basic/day | E4: DER | F4: MFC | G4: CBC | H4: 580 t1 | I4: 580 t2 | J4: 580 exc | K4: 180 first | L4: 180 exc | M4: 194 off | N4: 194 peak | O4: 195 so | P4: 195 off | Q4: 195 peak
A5: 2025-05 | B5: stale | C5: 0.122603 | D5: 0.54 | E5: 0.005554 | F5: 0.001886 | G5: 0.033 | H5: 0.1021 | I5: 0.1021 | J5: 0.0561 | K5: 0.1021 | L5: 0.1021 | M5: 0.0929 | N5: 0.1885 | O5: 0.045 | P5: 0.0929 | Q5: 0.244
A6: 2025-06 | B6: estimate | C6: 0.130053 | D6: 0.54 | E6: 0.005554 | F6: 0.001886 | G6: 0.033 | H6: 0.1064 | I6: 0.1348 | J6: 0.1348 | K6: 0.1064 | L6: 0.1348 | M6: 0.1093 | N6: 0.2217 | O6: 0.0452 | P6: 0.1388 | Q6: 0.2979
A7: 2025-07 | B7: estimate | C7: 0.118428 | D7: 0.54 | E7: 0.005554 | F7: 0.001886 | G7: 0.033 | H7: 0.1064 | I7: 0.1348 | J7: 0.1348 | K7: 0.1064 | L7: 0.1348 | M7: 0.1093 | N7: 0.2217 | O7: 0.0452 | P7: 0.1388 | Q7: 0.2979
A8: 2025-08 | B8: estimate | C8: 0.127798 | D8: 0.54 | E8: 0.005554 | F8: 0.001886 | G8: 0.033 | H8: 0.1064 | I8: 0.1348 | J8: 0.1348 | K8: 0.1064 | L8: 0.1348 | M8: 0.1093 | N8: 0.2217 | O8: 0.0452 | P8: 0.1388 | Q8: 0.2979
A9: 2025-09 | B9: estimate | C9: 0.130177 | D9: 0.54 | E9: 0.005554 | F9: 0.001886 | G9: 0.033 | H9: 0.1064 | I9: 0.1348 | J9: 0.1348 | K9: 0.1064 | L9: 0.1348 | M9: 0.1093 | N9: 0.2217 | O9: 0.0452 | P9: 0.1388 | Q9: 0.2979
A10: 2025-10 | B10: confirmed | C10: 0.129685 | D10: 0.54 | E10: 0.005554 | F10: 0.001886 | G10: 0.033 | H10: 0.1021 | I10: 0.1021 | J10: 0.0561 | K10: 0.1021 | L10: 0.1021 | M10: 0.0929 | N10: 0.1885 | O10: 0.045 | P10: 0.0929 | Q10: 0.244
A11: 2025-11 | B11: confirmed | C11: 0.127804 | D11: 0.54 | E11: 0.005554 | F11: 0.001886 | G11: 0.033 | H11: 0.1021 | I11: 0.1021 | J11: 0.0561 | K11: 0.1021 | L11: 0.1021 | M11: 0.0929 | N11: 0.1885 | O11: 0.045 | P11: 0.0929 | Q11: 0.244
A12: 2025-12 | B12: confirmed | C12: 0.125526 | D12: 0.54 | E12: 0.005554 | F12: 0.001886 | G12: 0.033 | H12: 0.1021 | I12: 0.1021 | J12: 0.0561 | K12: 0.1021 | L12: 0.1021 | M12: 0.0929 | N12: 0.1885 | O12: 0.045 | P12: 0.0929 | Q12: 0.244
A13: 2026-01 | B13: confirmed | C13: 0.129777 | D13: 0.56 | E13: 0.006014 | F13: 0.001763 | G13: 0.0372 | H13: 0.1064 | I13: 0.1064 | J13: 0.0585 | K13: 0.1064 | L13: 0.1064 | M13: 0.0929 | N13: 0.1885 | O13: 0.045 | P13: 0.0929 | Q13: 0.244
A14: 2026-02 | B14: confirmed | C14: 0.146948 | D14: 0.56 | E14: 0.006014 | F14: 0.001763 | G14: 0.0372 | H14: 0.1064 | I14: 0.1064 | J14: 0.0585 | K14: 0.1064 | L14: 0.1064 | M14: 0.0929 | N14: 0.1885 | O14: 0.045 | P14: 0.0929 | Q14: 0.244
A15: 2026-03 | B15: confirmed | C15: 0.165666 | D15: 0.56 | E15: 0.006014 | F15: 0.001763 | G15: 0.0372 | H15: 0.1064 | I15: 0.1064 | J15: 0.0585 | K15: 0.1064 | L15: 0.1064 | M15: 0.0929 | N15: 0.1885 | O15: 0.045 | P15: 0.0929 | Q15: 0.244
A16: 2026-04 | B16: confirmed | C16: 0.165927 | D16: 0.56 | E16: 0.006014 | F16: 0.001763 | G16: 0.0372 | H16: 0.1064 | I16: 0.1064 | J16: 0.0585 | K16: 0.1064 | L16: 0.1064 | M16: 0.0929 | N16: 0.1885 | O16: 0.045 | P16: 0.0929 | Q16: 0.244
A17: 2026-05 | B17: confirmed | C17: 0.160182 | D17: 0.56 | E17: 0.006014 | F17: 0.001763 | G17: 0.0372 | H17: 0.1064 | I17: 0.1064 | J17: 0.0585 | K17: 0.1064 | L17: 0.1064 | M17: 0.0929 | N17: 0.1885 | O17: 0.045 | P17: 0.0929 | Q17: 0.244

Sheet EffectiveRates
A1: EFFECTIVE RATES PER CYCLE (date-weighted from Rates schedule)
A2: Each value is the day-weighted average of the monthly schedule across the cycle - blends rate changes & seasons.
A4: Parameter | B4: Cycle 1 | C4: Cycle 2 | D4: Cycle 3 | E4: Cycle 4 | F4: Cycle 5 | G4: Cycle 6 | H4: Cycle 7 | I4: Cycle 8
A5: Basic service ($/day) | B5: 0.54 | C5: 0.54 | D5: 0.55 | E5: 0.56 | F5: 0.56 | G5: 0.56 | H5: 0.56 | I5: 0.56
A6: DER ($/kWh) | B6: 0.005554 | C6: 0.005554 | D6: 0.005784 | E6: 0.006014 | F6: 0.006014 | G6: 0.006014 | H6: 0.006014 | I6: 0.006014
A7: MFC ($/kWh) | B7: 0.001886 | C7: 0.001886 | D7: 0.001825 | E7: 0.001763 | F7: 0.001763 | G7: 0.001763 | H7: 0.001763 | I7: 0.001763
A8: CBC ($/kW/day) | B8: 0.033 | C8: 0.033 | D8: 0.0351 | E8: 0.0372 | F8: 0.0372 | G8: 0.0372 | H8: 0.0372 | I8: 0.0372
A9: Delivery Svc Adj ($/kWh) | B9: -0.0006 | C9: -0.0006 | D9: -0.0006 | E9: -0.0006 | F9: -0.0006 | G9: -0.0006 | H9: -0.0006 | I9: -0.0006
A10: Rev Decoupling Adj ($/kWh) | B10: -0.0003 | C10: -0.0003 | D10: -0.0003 | E10: -0.0003 | F10: -0.0003 | G10: -0.0003 | H10: -0.0003 | I10: -0.0003
A11: NY State Assmt (frac) | B11: 0.0027 | C11: 0.0027 | D11: 0.0027 | E11: 0.0027 | F11: 0.0027 | G11: 0.0027 | H11: 0.0027 | I11: 0.0027
A12: PILOTs (frac) | B12: 0.0215 | C12: 0.0215 | D12: 0.0215 | E12: 0.0215 | F12: 0.0215 | G12: 0.0215 | H12: 0.0215 | I12: 0.0215
A13: Suffolk Prop Tax (frac) | B13: 0.0231 | C13: 0.0231 | D13: 0.0231 | E13: 0.0231 | F13: 0.0231 | G13: 0.0231 | H13: 0.0231 | I13: 0.0231
A14: Sales tax (frac) | B14: 0.025 | C14: 0.025 | D14: 0.025 | E14: 0.025 | F14: 0.025 | G14: 0.025 | H14: 0.025 | I14: 0.025
A15: Supply rate ($/kWh) | B15: 0.127187 | C15: 0.126702 | D15: 0.127651 | E15: 0.137749 | F15: 0.156609 | G15: 0.165801 | H15: 0.162955 | I15: 0.160182
A16: 580 tier1 ($/kWh) | B16: 0.105204 | C16: 0.1021 | D16: 0.10425 | E16: 0.1064 | F16: 0.1064 | G16: 0.1064 | H16: 0.1064 | I16: 0.1064
... A30: 195 peak PSC x | B30: 1.805002 | C30: 1.9688 | D30: 1.9688 | E30: 1.9688 | F30: 1.9688 | G30: 1.9688 | H30: 1.9688 | I30: 1.9688
